sentry/__init__.py
sentry/command_service.py
sentry/command_task.py
sentry/configurable_service.py
sentry/configurable_task.py
sentry/constants.py
sentry/log_service.py
sentry/log_task.py
sentry/nop_service.py
sentry/nop_task.py
sentry/py.typed
sentry/service.py
sentry/task.py
sentry/task_service.py
sentry/wait2_service.py
sentry/wait2_task.py
sentry/wait_service.py
sentry/wait_task.py
py_sentry-1.6.0.dist-info/LICENSE.txt
py_sentry-1.6.0.dist-info/METADATA
py_sentry-1.6.0.dist-info/WHEEL
py_sentry-1.6.0.dist-info/entry_points.txt
py_sentry-1.6.0.dist-info/top_level.txt
py_sentry-1.6.0.dist-info/RECORD
